curdf/__init__.py
curdf/adapters.py
curdf/cell.py
curdf/neighbor.py
curdf/plotting.py
curdf/rdf.py
curdf-0.5.0.dist-info/licenses/LICENSE
curdf-0.5.0.dist-info/METADATA
curdf-0.5.0.dist-info/WHEEL
curdf-0.5.0.dist-info/top_level.txt
curdf-0.5.0.dist-info/RECORD
