Metadata-Version: 2.4
Name: cuRDF
Version: 0.5.0
Summary: GPU-accelerated radial distribution functions with NVIDIA ALCHEMI Toolkit-Ops neighbor lists and PyTorch.
Author: Joseph Hart
License-Expression: MIT
Project-URL: Homepage, https://github.com/joehart2001/cuRDF
Project-URL: Repository, https://github.com/joehart2001/cuRDF
Project-URL: Issues, https://github.com/joehart2001/cuRDF/issues
Project-URL: Documentation, https://github.com/joehart2001/cuRDF#readme
Project-URL: DOI, https://doi.org/10.5281/zenodo.1085332119
Keywords: rdf,radial distribution function,cuda,gpu,pytorch,neighbor list,molecular dynamics,ase,mdanalysis
Classifier: Development Status :: 4 - Beta
Classifier: Intended Audience :: Science/Research
Classifier: Intended Audience :: Developers
Classifier: Intended Audience :: Information Technology
Classifier: Programming Language :: Python :: 3
Classifier: Programming Language :: Python :: 3 :: Only
Classifier: Programming Language :: Python :: 3.10
Classifier: Programming Language :: Python :: 3.11
Classifier: Programming Language :: Python :: 3.12
Classifier: Operating System :: OS Independent
Classifier: Topic :: Scientific/Engineering
Classifier: Topic :: Scientific/Engineering :: Chemistry
Classifier: Topic :: Scientific/Engineering :: Physics
Classifier: Topic :: Scientific/Engineering :: Artificial Intelligence
Classifier: Topic :: Software Development :: Libraries
Classifier: Topic :: Software Development :: Libraries :: Python Modules
Classifier: Topic :: System :: Distributed Computing
Classifier: Topic :: Utilities
Requires-Python: >=3.10
License-File: LICENSE
Requires-Dist: numpy
Requires-Dist: torch>=2.8.0
Requires-Dist: nvalchemi-toolkit-ops>=0.2.0
Requires-Dist: MDAnalysis
Requires-Dist: ase
Requires-Dist: matplotlib
Provides-Extra: dev
Requires-Dist: pytest; extra == "dev"
Provides-Extra: docs
Requires-Dist: sphinx; extra == "docs"
Requires-Dist: sphinx-rtd-theme; extra == "docs"
Requires-Dist: myst-parser; extra == "docs"
Dynamic: license-file
